mframework/__init__.py
mframework/_docgen.py
mframework/_log.py
mframework/_mframework.py
mframework/_serialize.py
mframework/_utils.py
model_framework-0.1.0.dist-info/licenses/LICENSE.txt
model_framework-0.1.0.dist-info/METADATA
model_framework-0.1.0.dist-info/WHEEL
model_framework-0.1.0.dist-info/top_level.txt
model_framework-0.1.0.dist-info/RECORD
