Metadata-Version: 2.4
Name: model-framework
Version: 0.1.0
Summary: Framework to build consistent model interfaces
Home-page: https://github.com/airinnova/model-framework
Author: Aaron Dettmann
Author-email: dettmann@kth.se
License: Apache License 2.0
Classifier: Programming Language :: Python :: 3.11
Classifier: License :: OSI Approved :: Apache Software License
Classifier: Operating System :: OS Independent
Classifier: Intended Audience :: Developers
Classifier: Topic :: Scientific/Engineering
Requires-Python: >=3.11.11
License-File: LICENSE.txt
Requires-Dist: commonlibs
Requires-Dist: schemadict
Dynamic: author
Dynamic: author-email
Dynamic: classifier
Dynamic: description
Dynamic: home-page
Dynamic: license
Dynamic: license-file
Dynamic: requires-dist
Dynamic: requires-python
Dynamic: summary
